{
  "id": "image_gallery",
  "type": "SharedSlice",
  "name": "ImageGallery",
  "description": "ImageGallery",
  "variations": [
    {
      "id": "default-slice",
      "name": "Default slice",
      "docURL": "...",
      "version": "sktwi1xtmkfgx8626",
      "description": "ImageGallery",
      "primary": {
        "gallerySubTitle": {
          "config": {
            "label": "Gallery Sub Title",
            "placeholder": "",
            "allowTargetBlank": true,
            "single": "heading4,heading5,heading6"
          },
          "type": "StructuredText"
        },
        "galleryTitle": {
          "config": {
            "label": "Gallery Title",
            "placeholder": "This is where it all begins...",
            "allowTargetBlank": true,
            "single": "heading2,heading3,heading4"
          },
          "type": "StructuredText"
        },
        "galleryDescription": {
          "config": {
            "label": "Gallery Description",
            "placeholder": "",
            "allowTargetBlank": true,
            "multi": "paragraph,preformatted,heading1,heading2,heading3,heading4,heading5,heading6,strong,em,hyperlink,image,embed,list-item,o-list-item,rtl"
          },
          "type": "StructuredText"
        },
        "sectionId": {
          "config": {
            "label": "Section Id",
            "placeholder": ""
          },
          "type": "Text"
        },
        "class": {
          "config": {
            "label": "Class",
            "placeholder": ""
          },
          "type": "Text"
        }
      },
      "items": {
        "image": {
          "config": {
            "label": "Image",
            "constraint": {
              "width": null,
              "height": null
            },
            "thumbnails": []
          },
          "type": "Image"
        },
        "imageDescription": {
          "config": {
            "label": "Image Description",
            "placeholder": "",
            "allowTargetBlank": true,
            "single": "paragraph"
          },
          "type": "StructuredText"
        },
        "link": {
          "config": {
            "label": "Link",
            "placeholder": "",
            "allowTargetBlank": true
          },
          "type": "Link"
        },
        "linkLabel": {
          "config": {
            "label": "Link Label",
            "placeholder": ""
          },
          "type": "Text"
        }
      }
    }
  ]
}